aww/__init__.py
aww/athena/__init__.py
aww/athena/athena_query.py
aww/athena/bulk_inserter.py
aww/athena/context.py
aww/athena/query_manager.py
aww-0.0.2.dist-info/LICENSE
aww-0.0.2.dist-info/METADATA
aww-0.0.2.dist-info/WHEEL
aww-0.0.2.dist-info/top_level.txt
aww-0.0.2.dist-info/RECORD
