Metadata-Version: 2.1
Name: aww
Version: 0.0.2
Summary: AWS helper functions
Home-page: https://github.com/binarymason/aww
Author: John Mason
Author-email: binarymason@users.noreply.github.com
License: UNKNOWN
Project-URL: Bug Tracker, https://github.com/binarymason/aww/issues
Platform: UNKNOWN
Classifier: Programming Language :: Python :: 3
Classifier: License :: OSI Approved :: MIT License
Classifier: Operating System :: OS Independent
Requires-Python: >=3.6
